barman/__init__.py
barman/annotations.py
barman/backup.py
barman/backup_executor.py
barman/backup_manifest.py
barman/cli.py
barman/cloud.py
barman/command_wrappers.py
barman/compression.py
barman/config.py
barman/copy_controller.py
barman/diagnose.py
barman/encryption.py
barman/exceptions.py
barman/fs.py
barman/hooks.py
barman/infofile.py
barman/lockfile.py
barman/output.py
barman/postgres.py
barman/postgres_plumbing.py
barman/process.py
barman/recovery_executor.py
barman/remote_status.py
barman/retention_policies.py
barman/server.py
barman/utils.py
barman/version.py
barman/wal_archiver.py
barman/xlog.py
barman/clients/__init__.py
barman/clients/cloud_backup.py
barman/clients/cloud_backup_delete.py
barman/clients/cloud_backup_keep.py
barman/clients/cloud_backup_list.py
barman/clients/cloud_backup_show.py
barman/clients/cloud_check_wal_archive.py
barman/clients/cloud_cli.py
barman/clients/cloud_compression.py
barman/clients/cloud_restore.py
barman/clients/cloud_walarchive.py
barman/clients/cloud_walrestore.py
barman/clients/walarchive.py
barman/clients/walrestore.py
barman/cloud_providers/__init__.py
barman/cloud_providers/aws_s3.py
barman/cloud_providers/azure_blob_storage.py
barman/cloud_providers/google_cloud_storage.py
barman/storage/__init__.py
barman/storage/file_manager.py
barman/storage/file_stats.py
barman/storage/local_file_manager.py
barman-3.17.0.data/data/share/man/man1/barman-archive-wal.1
barman-3.17.0.data/data/share/man/man1/barman-backup.1
barman-3.17.0.data/data/share/man/man1/barman-check-backup.1
barman-3.17.0.data/data/share/man/man1/barman-check.1
barman-3.17.0.data/data/share/man/man1/barman-cloud-backup-delete.1
barman-3.17.0.data/data/share/man/man1/barman-cloud-backup-keep.1
barman-3.17.0.data/data/share/man/man1/barman-cloud-backup-list.1
barman-3.17.0.data/data/share/man/man1/barman-cloud-backup-show.1
barman-3.17.0.data/data/share/man/man1/barman-cloud-backup.1
barman-3.17.0.data/data/share/man/man1/barman-cloud-check-wal-archive.1
barman-3.17.0.dist-info/AUTHORS
barman-3.17.0.dist-info/LICENSE
barman-3.17.0.dist-info/METADATA
barman-3.17.0.dist-info/WHEEL
barman-3.17.0.dist-info/entry_points.txt
barman-3.17.0.dist-info/top_level.txt
barman-3.17.0.dist-info/RECORD
